Metadata-Version: 2.1
Name: dkbirdisland
Version: 0.1.4
Summary: DK, T-rex style
Home-page: https://github.com/Murilo-Gruppi/DonkeyKong-BirdIsland
Author: Murilo Castro
Author-email: murilo.castro@ccc.ufcg.edu.br
License: UNKNOWN
Platform: UNKNOWN
Classifier: Programming Language :: Python :: 3
Classifier: License :: OSI Approved :: MIT License
Classifier: Operating System :: OS Independent
Requires-Python: >=3.6
